pymiombo/__init__.py
pymiombo/gridi2qdgc.py
pymiombo/qdgc2gridi.py
tests/__init__.py
tests/gridi2qdgc.py
tests/qdgc2gridi.py
pyMiombo-0.1.1.dist-info/METADATA
pyMiombo-0.1.1.dist-info/WHEEL
pyMiombo-0.1.1.dist-info/top_level.txt
pyMiombo-0.1.1.dist-info/RECORD
