Metadata-Version: 2.1
Name: pyMiombo
Version: 0.1.1
Summary: WWF Python Library for Citizen Scientist with QDGC Functions
Author: Langen R. Mathew - lmathew@wwftz.org
License: MIT
